CHANGES.txt
README.txt
setup.py
OracleLibrary/__init__.py
OracleLibrary/_keywords.py
OracleLibrary/version.py
robotframework_OracleLibrary.egg-info/PKG-INFO
robotframework_OracleLibrary.egg-info/SOURCES.txt
robotframework_OracleLibrary.egg-info/dependency_links.txt
robotframework_OracleLibrary.egg-info/requires.txt
robotframework_OracleLibrary.egg-info/top_level.txt