Metadata-Version: 1.0
Name: robotframework-OracleLibrary
Version: 0.0.3-dev
Summary: Robot Framework Library to run sql queries against and Oracle DB
Home-page: https://code.google.com/p/robotframework-OracleLibrary/
Author: Jules Barnes
Author-email: jules@julesbarnes.com
License: LICENSE.txt
Platform: UNKNOWN
